code_topsis/101903700.py
code_topsis/__init__.py
101903700_Topsis_code-0.0.1.dist-info/LICENSE.txt
101903700_Topsis_code-0.0.1.dist-info/METADATA
101903700_Topsis_code-0.0.1.dist-info/WHEEL
101903700_Topsis_code-0.0.1.dist-info/top_level.txt
101903700_Topsis_code-0.0.1.dist-info/RECORD
