Metadata-Version: 2.1
Name: 101903700-Topsis-code
Version: 0.0.1
Summary: Topsis_code
Author: Bhavy Garg
Author-email: bgarg1_be19@thapar.edu
License: UNKNOWN
Keywords: topsis,Topsis
Platform: UNKNOWN
Classifier: Development Status :: 1 - Planning
Classifier: Intended Audience :: Developers
Classifier: Programming Language :: Python :: 3
Classifier: Operating System :: Unix
Classifier: Operating System :: MacOS :: MacOS X
Classifier: Operating System :: Microsoft :: Windows
License-File: LICENSE.txt
